api3_python_client/__init__.py
api3_python_client/api_credentials.py
api3_python_client/api_end_points.py
orbcomm_ais_api3_client-1.3.2.dist-info/LICENSE
orbcomm_ais_api3_client-1.3.2.dist-info/METADATA
orbcomm_ais_api3_client-1.3.2.dist-info/WHEEL
orbcomm_ais_api3_client-1.3.2.dist-info/top_level.txt
orbcomm_ais_api3_client-1.3.2.dist-info/RECORD
