Metadata-Version: 2.1
Name: orbcomm-ais-api3-client
Version: 1.3.2
Summary: Python client to access the ORBCOMM AIS API3
Author-email: ORBCOMM <service.customer@orbcomm.com>
Project-URL: Homepage, https://gitlab.com/orbcomm_ais_public/api3-python-client
Project-URL: Documentation, https://orbcomm_ais_public.gitlab.io/api3-python-client
Classifier: Programming Language :: Python :: 3
Classifier: License :: OSI Approved :: MIT License
Classifier: Operating System :: OS Independent
Requires-Python: >=3.9.13
License-File: LICENSE
